streamstate_utils/__init__.py
streamstate_utils/firestore.py
streamstate_utils/gcs_create_folder.py
streamstate_utils/generic_wrapper.py
streamstate_utils/k8s_utils.py
streamstate_utils/kafka_utils.py
streamstate_utils/pyspark_utils.py
streamstate_utils/run_test.py
streamstate_utils/spark_functions.py
streamstate_utils/structs.py
streamstate_utils/utils.py
streamstate_utils-0.14.0.dist-info/entry_points.txt
streamstate_utils-0.14.0.dist-info/WHEEL
streamstate_utils-0.14.0.dist-info/METADATA
streamstate_utils-0.14.0.dist-info/RECORD
